piptest988/__init__.py
piptest988-1.0.6.dist-info/METADATA
piptest988-1.0.6.dist-info/WHEEL
piptest988-1.0.6.dist-info/RECORD
