Metadata-Version: 2.1
Name: piptest988
Version: 1.0.6
Summary: Test module
Author: Your Name
Author-email: you@example.com
Requires-Python: >=3.10,<4.0
Classifier: Programming Language :: Python :: 3
Classifier: Programming Language :: Python :: 3.10
Classifier: Programming Language :: Python :: 3.11
Classifier: Programming Language :: Python :: 3.12
Requires-Dist: requests (>=2.31.0,<3.0.0)
Requires-Dist: tls-client (>=1.0.1,<2.0.0)
Requires-Dist: typing-extensions (>=4.9.0,<5.0.0)
